pre_commit_update/__init__.py
pre_commit_update/cli.py
pre_commit_update/managers/__init__.py
pre_commit_update/managers/env.py
pre_commit_update/managers/message.py
pre_commit_update/managers/option.py
pre_commit_update/managers/repo.py
pre_commit_update/managers/yaml.py
pre_commit_update/py.typed
pre_commit_update/repo.py
pre_commit_update/utils.py
pre_commit_update-0.9.0.dist-info/METADATA
pre_commit_update-0.9.0.dist-info/WHEEL
pre_commit_update-0.9.0.dist-info/entry_points.txt
pre_commit_update-0.9.0.dist-info/licenses/LICENSE
pre_commit_update-0.9.0.dist-info/RECORD
