Metadata-Version: 2.4
Name: pre-commit-update
Version: 0.9.0
Summary: Simple CLI tool and a pre-commit hook to check and update pre-commit hooks.
License-Expression: MIT
License-File: LICENSE
Author: Vojko Pribudić
Author-email: dmanthing@gmail.com
Maintainer: Vojko Pribudić
Maintainer-email: dmanthing@gmail.com
Requires-Python: >=3.10
Classifier: Development Status :: 5 - Production/Stable
Classifier: Environment :: Web Environment
Classifier: Intended Audience :: Developers
Classifier: License :: OSI Approved :: MIT License
Classifier: Natural Language :: English
Classifier: Operating System :: OS Independent
Classifier: Programming Language :: Python
Classifier: Programming Language :: Python :: 3
Classifier: Programming Language :: Python :: 3.10
Classifier: Programming Language :: Python :: 3.11
Classifier: Programming Language :: Python :: 3.12
Classifier: Programming Language :: Python :: 3.13
Classifier: Programming Language :: Python :: 3.14
Classifier: Programming Language :: Python :: 3 :: Only
Classifier: Topic :: Software Development :: Libraries
Requires-Dist: GitPython (>=3.1)
Requires-Dist: click (>=8.1)
Requires-Dist: packaging (>=24.0)
Requires-Dist: ruamel.yaml (>=0.18)
Requires-Dist: tomli (>=2.0.1)
Project-URL: changelog, https://gitlab.com/vojko.pribudic.foss/pre-commit-update/-/releases
Project-URL: issues, https://gitlab.com/vojko.pribudic.foss/pre-commit-update/-/issues
Project-URL: source, https://gitlab.com/vojko.pribudic.foss/pre-commit-update
